{
  "idea": [
    {
      "idea": "vvv",
      "userId": 1,
      "id": 1
    },
    {
      "idea": "jhgjkhgjkh",
      "userId": 1,
      "id": 2
    },
    {
      "idea": "fsdfsfsf",
      "userId": 1,
      "id": 3
    },
    {
      "idea": "fsdfsfsf, fjlskdjlsdk",
      "userId": 1,
      "id": 4
    }
  ],
  "users": [
    {
      "name": "test",
      "email": "test@email.com",
      "id": 1
    },
    {
      "name": "dek.haji",
      "email": "deeeqhaji@gmail.com",
      "id": 2
    },
    {
      "name": "ali",
      "email": "ali@email.com",
      "id": 3
    },
    {
      "name": "test1",
      "email": "test1@email.com",
      "id": 4
    },
    {
      "name": "Doly",
      "email": "dolly@email.com",
      "id": 5
    },
    {
      "name": "",
      "email": "",
      "id": 6
    },
    {
      "name": "dek.haji",
      "email": "deeeqhaji@gmail.com",
      "id": 7
    },
    {
      "name": "deeq",
      "email": "deeeqhaji@gmail.com",
      "id": 8
    }
  ]
}